ufotest/VERSION
ufotest/__init__.py
ufotest/_testing.py
ufotest/camera.py
ufotest/cli.py
ufotest/config.py
ufotest/exceptions.py
ufotest/install.py
ufotest/logging.py
ufotest/scripts.py
ufotest/testing.py
ufotest/util.py
ufotest/ci/__init__.py
ufotest/ci/build.py
ufotest/ci/mail.py
ufotest/ci/server.py
ufotest/ci/util.py
ufotest/scripts/IODELAY.sh
ufotest/scripts/IODELAY_Res.sh
ufotest/scripts/IODELAY_Set.sh
ufotest/scripts/PWDown.sh
ufotest/scripts/PWUp.sh
ufotest/scripts/Reset_all.sh
ufotest/scripts/Reset_all_TP.sh
ufotest/scripts/dma.sh
ufotest/scripts/fpga_conf.sh
ufotest/scripts/fpga_conf_bitprog.tcl
ufotest/scripts/fpga_conf_mcsgen.tcl
ufotest/scripts/fpga_conf_mcsprog.tcl
ufotest/scripts/pcie_init.sh
ufotest/scripts/reset_fpga.sh
ufotest/scripts/status.sh
ufotest/static/base.css
ufotest/static/favicon.ico
ufotest/static/list.css
ufotest/static/main.css
ufotest/static/photon_transfer_method.pdf
ufotest/static/report.css
ufotest/templates/archive_list.html
ufotest/templates/assertion_test_result.md
ufotest/templates/base.html
ufotest/templates/build_report.html
ufotest/templates/build_report.md
ufotest/templates/build_report.text
ufotest/templates/builds_list.html
ufotest/templates/default.toml
ufotest/templates/home.html
ufotest/templates/report_mail.html
ufotest/templates/report_mail.text
ufotest/templates/test_meta.md
ufotest/templates/test_report.html
ufotest/templates/test_report.md
ufotest/tests/basic.py
ufotest/tests/frame.py
ufotest/tests/installation.py
ufotest/tests/mock.py
ufotest/tests/setup.py
ufotest-1.1.0.dist-info/AUTHORS.rst
ufotest-1.1.0.dist-info/LICENSE
ufotest-1.1.0.dist-info/METADATA
ufotest-1.1.0.dist-info/WHEEL
ufotest-1.1.0.dist-info/entry_points.txt
ufotest-1.1.0.dist-info/top_level.txt
ufotest-1.1.0.dist-info/RECORD
