Metadata-Version: 2.1
Name: ufotest
Version: 1.1.0
Summary: CLI for setting up ufo camera test station
Home-page: https://github.com/the16thpythonist/ufotest
Author: Jonas Teufel
Author-email: jonseb1998@gmail.com
License: MIT license
Keywords: ufotest
Platform: UNKNOWN
Classifier: Development Status :: 2 - Pre-Alpha
Classifier: Intended Audience :: Developers
Classifier: License :: OSI Approved :: MIT License
Classifier: Natural Language :: English
Classifier: Programming Language :: Python :: 3
Classifier: Programming Language :: Python :: 3.5
Classifier: Programming Language :: Python :: 3.6
Classifier: Programming Language :: Python :: 3.7
Classifier: Programming Language :: Python :: 3.8
Requires-Python: >=3.5
Requires-Dist: Click (>=7.0)
Requires-Dist: flask (==1.1.2)
Requires-Dist: jinja2 (>=2.11.2)
Requires-Dist: matplotlib (>=3.3.0)
Requires-Dist: md-to-html (==0.7.0)
Requires-Dist: pillow (==7.0.0)
Requires-Dist: pytest-runner (==5.1)
Requires-Dist: pytest (==4.6.5)
Requires-Dist: toml (>=0.10.0)
